RCML/__init__.py
RCML-1.1.2.dist-info/LICENSE
RCML-1.1.2.dist-info/METADATA
RCML-1.1.2.dist-info/WHEEL
RCML-1.1.2.dist-info/top_level.txt
RCML-1.1.2.dist-info/RECORD
