Metadata-Version: 2.1
Name: RCML
Version: 1.1.2
Summary: Minimal implementations of classical ML algorithms
Home-page: https://github.com/piyush01123/Revisiting-Classical-ML
Author: Piyush Singh
License: MIT License        
License-File: LICENSE
Requires-Dist: pandas
Requires-Dist: numpy
Requires-Dist: scikit-learn
Requires-Dist: matplotlib
Requires-Dist: cvxpy
